example_package_fernandocaleo/__init__.py
example_package_fernandocaleo/gName.py
gname-0.0.1.dist-info/LICENSE
gname-0.0.1.dist-info/METADATA
gname-0.0.1.dist-info/WHEEL
gname-0.0.1.dist-info/top_level.txt
gname-0.0.1.dist-info/RECORD
