Metadata-Version: 2.1
Name: gname
Version: 0.0.1
Summary: Genera nombres y apellidos aleatoriamente
Author-email: fernando Caleo <fernando.caleo@gmail.com>
Project-URL: Homepage, https://github.com/fcaleo
Project-URL: Bug Tracker, https://github.com/fcaleo
Classifier: Programming Language :: Python :: 3
Classifier: License :: OSI Approved :: MIT License
Classifier: Operating System :: OS Independent
Requires-Python: >=3.7
License-File: LICENSE
